src/__init__.py
src/api.py
src/path.py
src/utils.py
src/components/__init__.py
src/components/errors/__init__.py
src/components/interceptor/__init__.py
src/components/interceptor/base.py
src/components/interceptor/manager.py
src/components/options/__init__.py
src/components/options/method.py
src/components/options/options.py
src/components/options/url.py
src/components/validator/__init__.py
src/components/validator/api.py
src/components/validator/base.py
src/components/validator/factory.py
src/components/validator/validators.py
src/core/__init__.py
src/core/utils.py
src/core/builder/__init__.py
src/core/builder/base.py
src/core/builder/builder.py
src/core/client/__init__.py
src/core/client/_client.py
src/core/client/_interceptors.py
src/core/client/base.py
src/core/client/factory.py
src/core/client/manager.py
src/core/conf/__init__.py
src/core/conf/base.py
src/core/conf/config.py
src/core/conf/generator.py
src/core/conf/reader.py
src/core/merge/__init__.py
src/core/merge/base.py
src/core/merge/merged.py
src/core/messages/__init__.py
src/core/messages/_mq.py
src/core/messages/base.py
src/types_of_py/__init__.py
w8_async_http-0.1.1.dist-info/LICENSE
w8_async_http-0.1.1.dist-info/METADATA
w8_async_http-0.1.1.dist-info/WHEEL
w8_async_http-0.1.1.dist-info/top_level.txt
w8_async_http-0.1.1.dist-info/RECORD
