Metadata-Version: 2.1
Name: w8-async-http
Version: 0.1.1
Summary: UNKNOWN
Home-page: UNKNOWN
Author: angel
Author-email: 376355670@qq.com
License: UNKNOWN
Platform: UNKNOWN
Classifier: Programming Language :: Python :: 3.7
Classifier: License :: OSI Approved :: MIT License
Classifier: Operating System :: POSIX
Classifier: Operating System :: MacOS
Classifier: Operating System :: POSIX :: Linux
Classifier: Operating System :: Unix
Classifier: Operating System :: Microsoft :: Windows
Classifier: Operating System :: OS Independent
Requires-Python: >=3.7
Requires-Dist: httpx (>=0.18.1)
